xlgcid.py
xlgcid-0.1.4.dist-info/LICENSE
xlgcid-0.1.4.dist-info/METADATA
xlgcid-0.1.4.dist-info/WHEEL
xlgcid-0.1.4.dist-info/RECORD
